deft_hep/ConfigReader.py
deft_hep/MCMCFitter.py
deft_hep/ModelValidator.py
deft_hep/PredictionBuilder.py
deft_hep/SummaryPlotter.py
deft_hep/__init__.py
deft_hep/helper.py
deft_hep-0.5.10.dist-info/LICENSE
deft_hep-0.5.10.dist-info/WHEEL
deft_hep-0.5.10.dist-info/METADATA
deft_hep-0.5.10.dist-info/RECORD
